pinn2dcm/__init__.py
pinn2dcm/__main__.py
pinn2dcm/pinn2dcm.py
pinn2dcm-1.0.0.data/scripts/__main__.py
pinn2dcm-1.0.0.dist-info/LICENSE
pinn2dcm-1.0.0.dist-info/METADATA
pinn2dcm-1.0.0.dist-info/WHEEL
pinn2dcm-1.0.0.dist-info/entry_points.txt
pinn2dcm-1.0.0.dist-info/top_level.txt
pinn2dcm-1.0.0.dist-info/RECORD
