Metadata-Version: 2.1
Name: pinn2dcm
Version: 1.0.0
Summary: A Python package to convert old Pinnacle CTs to the DICOM format
Home-page: https://github.com/sebasj13/Pinn2DCM
Author: Sebastian Schäfer
Author-email: se.schaefer@uke.de
Project-URL: Bug Tracker, https://github.com/sebasj13/Pinn2DCM/issues
Keywords: DICOM,Pinnacle,CT,Radiation Therapy,RT
Classifier: Programming Language :: Python :: 3
Classifier: License :: OSI Approved :: MIT License
Classifier: Operating System :: OS Independent
Requires-Python: >=3
License-File: LICENSE
Requires-Dist: numpy
Requires-Dist: pydicom
